qf
setup.py
quickfind/Console.py
quickfind/Orderer.py
quickfind/Searcher.py
quickfind/__init__.py
quickfind.egg-info/PKG-INFO
quickfind.egg-info/SOURCES.txt
quickfind.egg-info/dependency_links.txt
quickfind.egg-info/requires.txt
quickfind.egg-info/top_level.txt
quickfind/source/CtagsSource.py
quickfind/source/DirectorySource.py
quickfind/source/Source.py
quickfind/source/Util.py
quickfind/source/__init__.py