Metadata-Version: 1.1
Name: quickfind
Version: 0.3.3.1
Summary: Fuzzy find for the terminal
Home-page: https://github.com/Refefer/quickfind
Author: Andrew Stanton
Author-email: Andrew Stanton
License: LICENSE
Platform: UNKNOWN
Classifier: License :: OSI Approved :: Apache Software License
Classifier: Programming Language :: Python :: 2.7
Classifier: Programming Language :: Python :: 3.2
Classifier: Operating System :: OS Independent
